HISTORY.md
LICENSE
MANIFEST.in
README.md
requirements.txt
setup.py
coincheck/__init__.py
coincheck/account.py
coincheck/market.py
coincheck/order.py
coincheck/utils.py
coincheck.egg-info/PKG-INFO
coincheck.egg-info/PKG-INFOe
coincheck.egg-info/PKG-INFOee
coincheck.egg-info/SOURCES.txt
coincheck.egg-info/dependency_links.txt
coincheck.egg-info/not-zip-safe
coincheck.egg-info/requires.txt
coincheck.egg-info/top_level.txt