Metadata-Version: 1.1
Name: coincheck
Version: 0.1.10
Summary: Coincheck API Library for Python
Home-page: https://github.com/kmn/coincheck
Author: Shohei Kamon
Author-email: kamonshohei@gmail.com
License: MIT
Platform: UNKNOWN
Classifier: b'Development Status :: 5 - Production/Stable'
Classifier: b'Intended Audience :: Developers'
Classifier: b'Natural Language :: English'
Classifier: b'License :: OSI Approved :: MIT License'
Classifier: b'Programming Language :: Python'
Classifier: b'Programming Language :: Python :: 2.7'
Classifier: b'Programming Language :: Python :: 3'
Classifier: b'Programming Language :: Python :: 3.3'
